sqlite3dict/__init__.py
sqlite3dict/collection.py
sqlite3dict/storage.py
sqlite3dict/test.py
sqlite3dict/common/__init__.py
sqlite3dict/common/safejson.py
sqlite3dict/crud/__init__.py
sqlite3dict/crud/delete.py
sqlite3dict/crud/insert.py
sqlite3dict/crud/query.py
sqlite3dict/crud/safejson.py
sqlite3dict/crud/update.py
sqlite3dict-1.0.1.dist-info/LICENSE
sqlite3dict-1.0.1.dist-info/METADATA
sqlite3dict-1.0.1.dist-info/WHEEL
sqlite3dict-1.0.1.dist-info/top_level.txt
sqlite3dict-1.0.1.dist-info/RECORD
